{
    "content": "Sindy Chen\nin\nMarketing Strategist . Taipei . TW . sindy.chen@cakeresume.com Economics graduate with proven writing & marketing skills. Serving as Content Strategist, to convey core value of CakeResume, and enhance website & keywords ranking via SEO strategies. Passionate about learning and growing in a company with a dynamic working environment.\nWork & Internship Experience\nCakeResume \u00b7 Content Marketing Strategist\nOct 2019 - Present 9 Taipei, Taiwan\nwrote series of articles to convey core value of CakeResume\nenhanced website & keywords ranking through SEO strategies\nenhanced users' interaction and conversion rate through content strategies\nMotivation: to learn and grow at the Talent Resource startup with great potential\nCake Resume\nAsia Silicon Valley Program . Stationed Intern Jun 2019 - Aug 2019 9 Bangkok, Thailand\ncontacted 50- companies, and reached initial cooperation agreement with 3\nconducted research on Thai banking system. FinTech startups & medical industry\ndeveloped business and human network in both Taiwan and Thailand\nMotivation: to explore new business opportunities and build up connection in Thailand\nRookie Fund . Investment Partner\nOct 2018 - Jun 2019 9 Taipei, Taiwan\ngot in touch with 30- startup teams, and performed due diligence investigation on 10 startups\norganized 2 sharing & matching activities cooperatively, and attracted 50+ participants\nconducted investment risk assessment on 2 companies, and competed 1 investment\nMotivation: to understand how venture capitalists analyze startups while making investment decisions\nR ROOICIE FUND\nEducation\nNational Tsing Hua University . BEc . 2015 - 2019 Major : Economics . GPA : 3.92 / 4.3 0 Hsinchu, Taiwan",
    "styles": [],
    "pages": [
        {
            "page_number": 1,
            "width": 644.0,
            "height": 889.0,
            "unit": "pixel",
            "lines": [
                {
                    "content": "Sindy Chen",
                    "bounding_box": [
                        {
                            "x": 270.0,
                            "y": 134.0
                        },
                        {
                            "x": 372.0,
                            "y": 134.0
                        },
                        {
                            "x": 372.0,
                            "y": 157.0
                        },
                        {
                            "x": 269.0,
                            "y": 156.0
                        }
                    ]
                },
                {
                    "content": "in",
                    "bounding_box": [
                        {
                            "x": 312.0,
                            "y": 168.0
                        },
                        {
                            "x": 327.0,
                            "y": 168.0
                        },
                        {
                            "x": 327.0,
                            "y": 183.0
                        },
                        {
                            "x": 312.0,
                            "y": 183.0
                        }
                    ]
                },
                {
                    "content": "Marketing Strategist . Taipei . TW . sindy.chen@cakeresume.com",
                    "bounding_box": [
                        {
                            "x": 131.0,
                            "y": 202.0
                        },
                        {
                            "x": 511.0,
                            "y": 202.0
                        },
                        {
                            "x": 511.0,
                            "y": 219.0
                        },
                        {
                            "x": 131.0,
                            "y": 219.0
                        }
                    ]
                },
                {
                    "content": "Economics graduate with proven writing & marketing skills. Serving as Content Strategist, to convey",
                    "bounding_box": [
                        {
                            "x": 89.0,
                            "y": 226.0
                        },
                        {
                            "x": 553.0,
                            "y": 226.0
                        },
                        {
                            "x": 553.0,
                            "y": 240.0
                        },
                        {
                            "x": 89.0,
                            "y": 240.0
                        }
                    ]
                },
                {
                    "content": "core value of CakeResume, and enhance website & keywords ranking via SEO strategies.",
                    "bounding_box": [
                        {
                            "x": 113.0,
                            "y": 241.0
                        },
                        {
                            "x": 528.0,
                            "y": 241.0
                        },
                        {
                            "x": 528.0,
                            "y": 255.0
                        },
                        {
                            "x": 113.0,
                            "y": 255.0
                        }
                    ]
                },
                {
                    "content": "Passionate about learning and growing in a company with a dynamic working environment.",
                    "bounding_box": [
                        {
                            "x": 107.0,
                            "y": 256.0
                        },
                        {
                            "x": 534.0,
                            "y": 257.0
                        },
                        {
                            "x": 534.0,
                            "y": 271.0
                        },
                        {
                            "x": 107.0,
                            "y": 271.0
                        }
                    ]
                },
                {
                    "content": "Work & Internship Experience",
                    "bounding_box": [
                        {
                            "x": 37.0,
                            "y": 335.0
                        },
                        {
                            "x": 309.0,
                            "y": 335.0
                        },
                        {
                            "x": 309.0,
                            "y": 357.0
                        },
                        {
                            "x": 37.0,
                            "y": 356.0
                        }
                    ]
                },
                {
                    "content": "CakeResume \u00b7 Content Marketing Strategist",
                    "bounding_box": [
                        {
                            "x": 86.0,
                            "y": 366.0
                        },
                        {
                            "x": 342.0,
                            "y": 366.0
                        },
                        {
                            "x": 342.0,
                            "y": 383.0
                        },
                        {
                            "x": 86.0,
                            "y": 382.0
                        }
                    ]
                },
                {
                    "content": "Oct 2019 - Present 9 Taipei, Taiwan",
                    "bounding_box": [
                        {
                            "x": 86.0,
                            "y": 390.0
                        },
                        {
                            "x": 262.0,
                            "y": 390.0
                        },
                        {
                            "x": 262.0,
                            "y": 405.0
                        },
                        {
                            "x": 86.0,
                            "y": 404.0
                        }
                    ]
                },
                {
                    "content": "wrote series of articles to convey core value of CakeResume",
                    "bounding_box": [
                        {
                            "x": 103.0,
                            "y": 411.0
                        },
                        {
                            "x": 357.0,
                            "y": 411.0
                        },
                        {
                            "x": 357.0,
                            "y": 423.0
                        },
                        {
                            "x": 103.0,
                            "y": 423.0
                        }
                    ]
                },
                {
                    "content": "enhanced website & keywords ranking through SEO strategies",
                    "bounding_box": [
                        {
                            "x": 110.0,
                            "y": 424.0
                        },
                        {
                            "x": 366.0,
                            "y": 424.0
                        },
                        {
                            "x": 366.0,
                            "y": 436.0
                        },
                        {
                            "x": 110.0,
                            "y": 436.0
                        }
                    ]
                },
                {
                    "content": "enhanced users' interaction and conversion rate through content strategies",
                    "bounding_box": [
                        {
                            "x": 110.0,
                            "y": 436.0
                        },
                        {
                            "x": 421.0,
                            "y": 437.0
                        },
                        {
                            "x": 421.0,
                            "y": 449.0
                        },
                        {
                            "x": 110.0,
                            "y": 448.0
                        }
                    ]
                },
                {
                    "content": "Motivation: to learn and grow at the Talent Resource startup with great potential",
                    "bounding_box": [
                        {
                            "x": 111.0,
                            "y": 449.0
                        },
                        {
                            "x": 442.0,
                            "y": 449.0
                        },
                        {
                            "x": 442.0,
                            "y": 460.0
                        },
                        {
                            "x": 111.0,
                            "y": 460.0
                        }
                    ]
                },
                {
                    "content": "Cake",
                    "bounding_box": [
                        {
                            "x": 556.0,
                            "y": 391.0
                        },
                        {
                            "x": 585.0,
                            "y": 392.0
                        },
                        {
                            "x": 584.0,
                            "y": 404.0
                        },
                        {
                            "x": 555.0,
                            "y": 402.0
                        }
                    ]
                },
                {
                    "content": "Resume",
                    "bounding_box": [
                        {
                            "x": 556.0,
                            "y": 403.0
                        },
                        {
                            "x": 598.0,
                            "y": 404.0
                        },
                        {
                            "x": 598.0,
                            "y": 414.0
                        },
                        {
                            "x": 556.0,
                            "y": 414.0
                        }
                    ]
                },
                {
                    "content": "Asia Silicon Valley Program . Stationed Intern",
                    "bounding_box": [
                        {
                            "x": 85.0,
                            "y": 479.0
                        },
                        {
                            "x": 350.0,
                            "y": 480.0
                        },
                        {
                            "x": 350.0,
                            "y": 496.0
                        },
                        {
                            "x": 85.0,
                            "y": 496.0
                        }
                    ]
                },
                {
                    "content": "Jun 2019 - Aug 2019 9 Bangkok, Thailand",
                    "bounding_box": [
                        {
                            "x": 85.0,
                            "y": 503.0
                        },
                        {
                            "x": 287.0,
                            "y": 503.0
                        },
                        {
                            "x": 287.0,
                            "y": 518.0
                        },
                        {
                            "x": 85.0,
                            "y": 518.0
                        }
                    ]
                },
                {
                    "content": "contacted 50- companies, and reached initial cooperation agreement with 3",
                    "bounding_box": [
                        {
                            "x": 104.0,
                            "y": 524.0
                        },
                        {
                            "x": 423.0,
                            "y": 525.0
                        },
                        {
                            "x": 423.0,
                            "y": 537.0
                        },
                        {
                            "x": 104.0,
                            "y": 537.0
                        }
                    ]
                },
                {
                    "content": "conducted research on Thai banking system. FinTech startups & medical industry",
                    "bounding_box": [
                        {
                            "x": 109.0,
                            "y": 537.0
                        },
                        {
                            "x": 442.0,
                            "y": 537.0
                        },
                        {
                            "x": 442.0,
                            "y": 549.0
                        },
                        {
                            "x": 109.0,
                            "y": 549.0
                        }
                    ]
                },
                {
                    "content": "developed business and human network in both Taiwan and Thailand",
                    "bounding_box": [
                        {
                            "x": 111.0,
                            "y": 550.0
                        },
                        {
                            "x": 397.0,
                            "y": 550.0
                        },
                        {
                            "x": 397.0,
                            "y": 561.0
                        },
                        {
                            "x": 111.0,
                            "y": 561.0
                        }
                    ]
                },
                {
                    "content": "Motivation: to explore new business opportunities and build up connection in Thailand",
                    "bounding_box": [
                        {
                            "x": 104.0,
                            "y": 562.0
                        },
                        {
                            "x": 467.0,
                            "y": 562.0
                        },
                        {
                            "x": 467.0,
                            "y": 574.0
                        },
                        {
                            "x": 104.0,
                            "y": 574.0
                        }
                    ]
                },
                {
                    "content": "Rookie Fund . Investment Partner",
                    "bounding_box": [
                        {
                            "x": 86.0,
                            "y": 594.0
                        },
                        {
                            "x": 285.0,
                            "y": 594.0
                        },
                        {
                            "x": 285.0,
                            "y": 609.0
                        },
                        {
                            "x": 86.0,
                            "y": 608.0
                        }
                    ]
                },
                {
                    "content": "Oct 2018 - Jun 2019 9 Taipei, Taiwan",
                    "bounding_box": [
                        {
                            "x": 88.0,
                            "y": 617.0
                        },
                        {
                            "x": 268.0,
                            "y": 617.0
                        },
                        {
                            "x": 268.0,
                            "y": 631.0
                        },
                        {
                            "x": 88.0,
                            "y": 631.0
                        }
                    ]
                },
                {
                    "content": "got in touch with 30- startup teams, and performed due diligence investigation on 10 startups",
                    "bounding_box": [
                        {
                            "x": 104.0,
                            "y": 638.0
                        },
                        {
                            "x": 496.0,
                            "y": 638.0
                        },
                        {
                            "x": 496.0,
                            "y": 651.0
                        },
                        {
                            "x": 104.0,
                            "y": 651.0
                        }
                    ]
                },
                {
                    "content": "organized 2 sharing & matching activities cooperatively, and attracted 50+ participants",
                    "bounding_box": [
                        {
                            "x": 109.0,
                            "y": 651.0
                        },
                        {
                            "x": 464.0,
                            "y": 651.0
                        },
                        {
                            "x": 464.0,
                            "y": 663.0
                        },
                        {
                            "x": 109.0,
                            "y": 663.0
                        }
                    ]
                },
                {
                    "content": "conducted investment risk assessment on 2 companies, and competed 1 investment",
                    "bounding_box": [
                        {
                            "x": 111.0,
                            "y": 664.0
                        },
                        {
                            "x": 456.0,
                            "y": 663.0
                        },
                        {
                            "x": 456.0,
                            "y": 675.0
                        },
                        {
                            "x": 111.0,
                            "y": 675.0
                        }
                    ]
                },
                {
                    "content": "Motivation: to understand how venture capitalists analyze startups while making investment",
                    "bounding_box": [
                        {
                            "x": 110.0,
                            "y": 676.0
                        },
                        {
                            "x": 490.0,
                            "y": 676.0
                        },
                        {
                            "x": 490.0,
                            "y": 688.0
                        },
                        {
                            "x": 110.0,
                            "y": 688.0
                        }
                    ]
                },
                {
                    "content": "decisions",
                    "bounding_box": [
                        {
                            "x": 111.0,
                            "y": 689.0
                        },
                        {
                            "x": 151.0,
                            "y": 690.0
                        },
                        {
                            "x": 151.0,
                            "y": 700.0
                        },
                        {
                            "x": 111.0,
                            "y": 700.0
                        }
                    ]
                },
                {
                    "content": "R",
                    "bounding_box": [
                        {
                            "x": 560.0,
                            "y": 595.0
                        },
                        {
                            "x": 599.0,
                            "y": 594.0
                        },
                        {
                            "x": 599.0,
                            "y": 638.0
                        },
                        {
                            "x": 559.0,
                            "y": 637.0
                        }
                    ]
                },
                {
                    "content": "ROOICIE FUND",
                    "bounding_box": [
                        {
                            "x": 559.0,
                            "y": 638.0
                        },
                        {
                            "x": 602.0,
                            "y": 638.0
                        },
                        {
                            "x": 602.0,
                            "y": 644.0
                        },
                        {
                            "x": 559.0,
                            "y": 643.0
                        }
                    ]
                },
                {
                    "content": "Education",
                    "bounding_box": [
                        {
                            "x": 38.0,
                            "y": 772.0
                        },
                        {
                            "x": 130.0,
                            "y": 772.0
                        },
                        {
                            "x": 130.0,
                            "y": 791.0
                        },
                        {
                            "x": 37.0,
                            "y": 791.0
                        }
                    ]
                },
                {
                    "content": "National Tsing Hua University . BEc . 2015 - 2019",
                    "bounding_box": [
                        {
                            "x": 86.0,
                            "y": 803.0
                        },
                        {
                            "x": 374.0,
                            "y": 803.0
                        },
                        {
                            "x": 374.0,
                            "y": 818.0
                        },
                        {
                            "x": 86.0,
                            "y": 819.0
                        }
                    ]
                },
                {
                    "content": "Major : Economics . GPA : 3.92 / 4.3 0 Hsinchu, Taiwan",
                    "bounding_box": [
                        {
                            "x": 86.0,
                            "y": 826.0
                        },
                        {
                            "x": 351.0,
                            "y": 826.0
                        },
                        {
                            "x": 351.0,
                            "y": 841.0
                        },
                        {
                            "x": 86.0,
                            "y": 841.0
                        }
                    ]
                }
            ],
            "words": [
                {
                    "content": "Sindy",
                    "confidence": 0.997
                },
                {
                    "content": "Chen",
                    "confidence": 0.988
                },
                {
                    "content": "in",
                    "confidence": 0.997
                },
                {
                    "content": "Marketing",
                    "confidence": 0.993
                },
                {
                    "content": "Strategist",
                    "confidence": 0.993
                },
                {
                    "content": ".",
                    "confidence": 0.669
                },
                {
                    "content": "Taipei",
                    "confidence": 0.994
                },
                {
                    "content": ".",
                    "confidence": 0.254
                },
                {
                    "content": "TW",
                    "confidence": 0.997
                },
                {
                    "content": ".",
                    "confidence": 0.622
                },
                {
                    "content": "sindy.chen@cakeresume.com",
                    "confidence": 0.955
                },
                {
                    "content": "Economics",
                    "confidence": 0.97
                },
                {
                    "content": "graduate",
                    "confidence": 0.994
                },
                {
                    "content": "with",
                    "confidence": 0.987
                },
                {
                    "content": "proven",
                    "confidence": 0.994
                },
                {
                    "content": "writing",
                    "confidence": 0.994
                },
                {
                    "content": "&",
                    "confidence": 0.995
                },
                {
                    "content": "marketing",
                    "confidence": 0.993
                },
                {
                    "content": "skills.",
                    "confidence": 0.957
                },
                {
                    "content": "Serving",
                    "confidence": 0.995
                },
                {
                    "content": "as",
                    "confidence": 0.996
                },
                {
                    "content": "Content",
                    "confidence": 0.991
                },
                {
                    "content": "Strategist,",
                    "confidence": 0.983
                },
                {
                    "content": "to",
                    "confidence": 0.995
                },
                {
                    "content": "convey",
                    "confidence": 0.996
                },
                {
                    "content": "core",
                    "confidence": 0.987
                },
                {
                    "content": "value",
                    "confidence": 0.997
                },
                {
                    "content": "of",
                    "confidence": 0.997
                },
                {
                    "content": "CakeResume,",
                    "confidence": 0.991
                },
                {
                    "content": "and",
                    "confidence": 0.998
                },
                {
                    "content": "enhance",
                    "confidence": 0.995
                },
                {
                    "content": "website",
                    "confidence": 0.994
                },
                {
                    "content": "&",
                    "confidence": 0.997
                },
                {
                    "content": "keywords",
                    "confidence": 0.993
                },
                {
                    "content": "ranking",
                    "confidence": 0.995
                },
                {
                    "content": "via",
                    "confidence": 0.995
                },
                {
                    "content": "SEO",
                    "confidence": 0.993
                },
                {
                    "content": "strategies.",
                    "confidence": 0.962
                },
                {
                    "content": "Passionate",
                    "confidence": 0.993
                },
                {
                    "content": "about",
                    "confidence": 0.997
                },
                {
                    "content": "learning",
                    "confidence": 0.802
                },
                {
                    "content": "and",
                    "confidence": 0.998
                },
                {
                    "content": "growing",
                    "confidence": 0.995
                },
                {
                    "content": "in",
                    "confidence": 0.997
                },
                {
                    "content": "a",
                    "confidence": 0.991
                },
                {
                    "content": "company",
                    "confidence": 0.995
                },
                {
                    "content": "with",
                    "confidence": 0.991
                },
                {
                    "content": "a",
                    "confidence": 0.991
                },
                {
                    "content": "dynamic",
                    "confidence": 0.994
                },
                {
                    "content": "working",
                    "confidence": 0.886
                },
                {
                    "content": "environment.",
                    "confidence": 0.963
                },
                {
                    "content": "Work",
                    "confidence": 0.988
                },
                {
                    "content": "&",
                    "confidence": 0.991
                },
                {
                    "content": "Internship",
                    "confidence": 0.991
                },
                {
                    "content": "Experience",
                    "confidence": 0.994
                },
                {
                    "content": "CakeResume",
                    "confidence": 0.994
                },
                {
                    "content": "\u00b7",
                    "confidence": 0.439
                },
                {
                    "content": "Content",
                    "confidence": 0.996
                },
                {
                    "content": "Marketing",
                    "confidence": 0.995
                },
                {
                    "content": "Strategist",
                    "confidence": 0.994
                },
                {
                    "content": "Oct",
                    "confidence": 0.995
                },
                {
                    "content": "2019",
                    "confidence": 0.991
                },
                {
                    "content": "-",
                    "confidence": 0.99
                },
                {
                    "content": "Present",
                    "confidence": 0.995
                },
                {
                    "content": "9",
                    "confidence": 0.646
                },
                {
                    "content": "Taipei,",
                    "confidence": 0.981
                },
                {
                    "content": "Taiwan",
                    "confidence": 0.995
                },
                {
                    "content": "wrote",
                    "confidence": 0.994
                },
                {
                    "content": "series",
                    "confidence": 0.993
                },
                {
                    "content": "of",
                    "confidence": 0.997
                },
                {
                    "content": "articles",
                    "confidence": 0.967
                },
                {
                    "content": "to",
                    "confidence": 0.997
                },
                {
                    "content": "convey",
                    "confidence": 0.993
                },
                {
                    "content": "core",
                    "confidence": 0.985
                },
                {
                    "content": "value",
                    "confidence": 0.992
                },
                {
                    "content": "of",
                    "confidence": 0.993
                },
                {
                    "content": "CakeResume",
                    "confidence": 0.957
                },
                {
                    "content": "enhanced",
                    "confidence": 0.994
                },
                {
                    "content": "website",
                    "confidence": 0.991
                },
                {
                    "content": "&",
                    "confidence": 0.997
                },
                {
                    "content": "keywords",
                    "confidence": 0.994
                },
                {
                    "content": "ranking",
                    "confidence": 0.995
                },
                {
                    "content": "through",
                    "confidence": 0.993
                },
                {
                    "content": "SEO",
                    "confidence": 0.881
                },
                {
                    "content": "strategies",
                    "confidence": 0.604
                },
                {
                    "content": "enhanced",
                    "confidence": 0.989
                },
                {
                    "content": "users'",
                    "confidence": 0.991
                },
                {
                    "content": "interaction",
                    "confidence": 0.987
                },
                {
                    "content": "and",
                    "confidence": 0.997
                },
                {
                    "content": "conversion",
                    "confidence": 0.956
                },
                {
                    "content": "rate",
                    "confidence": 0.982
                },
                {
                    "content": "through",
                    "confidence": 0.993
                },
                {
                    "content": "content",
                    "confidence": 0.995
                },
                {
                    "content": "strategies",
                    "confidence": 0.969
                },
                {
                    "content": "Motivation:",
                    "confidence": 0.901
                },
                {
                    "content": "to",
                    "confidence": 0.997
                },
                {
                    "content": "learn",
                    "confidence": 0.991
                },
                {
                    "content": "and",
                    "confidence": 0.998
                },
                {
                    "content": "grow",
                    "confidence": 0.987
                },
                {
                    "content": "at",
                    "confidence": 0.997
                },
                {
                    "content": "the",
                    "confidence": 0.993
                },
                {
                    "content": "Talent",
                    "confidence": 0.996
                },
                {
                    "content": "Resource",
                    "confidence": 0.984
                },
                {
                    "content": "startup",
                    "confidence": 0.992
                },
                {
                    "content": "with",
                    "confidence": 0.988
                },
                {
                    "content": "great",
                    "confidence": 0.996
                },
                {
                    "content": "potential",
                    "confidence": 0.941
                },
                {
                    "content": "Cake",
                    "confidence": 0.97
                },
                {
                    "content": "Resume",
                    "confidence": 0.997
                },
                {
                    "content": "Asia",
                    "confidence": 0.984
                },
                {
                    "content": "Silicon",
                    "confidence": 0.993
                },
                {
                    "content": "Valley",
                    "confidence": 0.997
                },
                {
                    "content": "Program",
                    "confidence": 0.996
                },
                {
                    "content": ".",
                    "confidence": 0.617
                },
                {
                    "content": "Stationed",
                    "confidence": 0.994
                },
                {
                    "content": "Intern",
                    "confidence": 0.991
                },
                {
                    "content": "Jun",
                    "confidence": 0.987
                },
                {
                    "content": "2019",
                    "confidence": 0.991
                },
                {
                    "content": "-",
                    "confidence": 0.993
                },
                {
                    "content": "Aug",
                    "confidence": 0.997
                },
                {
                    "content": "2019",
                    "confidence": 0.992
                },
                {
                    "content": "9",
                    "confidence": 0.032
                },
                {
                    "content": "Bangkok,",
                    "confidence": 0.953
                },
                {
                    "content": "Thailand",
                    "confidence": 0.991
                },
                {
                    "content": "contacted",
                    "confidence": 0.991
                },
                {
                    "content": "50-",
                    "confidence": 0.804
                },
                {
                    "content": "companies,",
                    "confidence": 0.845
                },
                {
                    "content": "and",
                    "confidence": 0.997
                },
                {
                    "content": "reached",
                    "confidence": 0.994
                },
                {
                    "content": "initial",
                    "confidence": 0.941
                },
                {
                    "content": "cooperation",
                    "confidence": 0.993
                },
                {
                    "content": "agreement",
                    "confidence": 0.993
                },
                {
                    "content": "with",
                    "confidence": 0.986
                },
                {
                    "content": "3",
                    "confidence": 0.991
                },
                {
                    "content": "conducted",
                    "confidence": 0.993
                },
                {
                    "content": "research",
                    "confidence": 0.994
                },
                {
                    "content": "on",
                    "confidence": 0.997
                },
                {
                    "content": "Thai",
                    "confidence": 0.991
                },
                {
                    "content": "banking",
                    "confidence": 0.993
                },
                {
                    "content": "system.",
                    "confidence": 0.803
                },
                {
                    "content": "FinTech",
                    "confidence": 0.993
                },
                {
                    "content": "startups",
                    "confidence": 0.992
                },
                {
                    "content": "&",
                    "confidence": 0.981
                },
                {
                    "content": "medical",
                    "confidence": 0.991
                },
                {
                    "content": "industry",
                    "confidence": 0.994
                },
                {
                    "content": "developed",
                    "confidence": 0.993
                },
                {
                    "content": "business",
                    "confidence": 0.976
                },
                {
                    "content": "and",
                    "confidence": 0.997
                },
                {
                    "content": "human",
                    "confidence": 0.996
                },
                {
                    "content": "network",
                    "confidence": 0.993
                },
                {
                    "content": "in",
                    "confidence": 0.997
                },
                {
                    "content": "both",
                    "confidence": 0.983
                },
                {
                    "content": "Taiwan",
                    "confidence": 0.606
                },
                {
                    "content": "and",
                    "confidence": 0.997
                },
                {
                    "content": "Thailand",
                    "confidence": 0.993
                },
                {
                    "content": "Motivation:",
                    "confidence": 0.957
                },
                {
                    "content": "to",
                    "confidence": 0.997
                },
                {
                    "content": "explore",
                    "confidence": 0.992
                },
                {
                    "content": "new",
                    "confidence": 0.997
                },
                {
                    "content": "business",
                    "confidence": 0.993
                },
                {
                    "content": "opportunities",
                    "confidence": 0.98
                },
                {
                    "content": "and",
                    "confidence": 0.997
                },
                {
                    "content": "build",
                    "confidence": 0.994
                },
                {
                    "content": "up",
                    "confidence": 0.995
                },
                {
                    "content": "connection",
                    "confidence": 0.993
                },
                {
                    "content": "in",
                    "confidence": 0.997
                },
                {
                    "content": "Thailand",
                    "confidence": 0.991
                },
                {
                    "content": "Rookie",
                    "confidence": 0.996
                },
                {
                    "content": "Fund",
                    "confidence": 0.988
                },
                {
                    "content": ".",
                    "confidence": 0.121
                },
                {
                    "content": "Investment",
                    "confidence": 0.991
                },
                {
                    "content": "Partner",
                    "confidence": 0.995
                },
                {
                    "content": "Oct",
                    "confidence": 0.996
                },
                {
                    "content": "2018",
                    "confidence": 0.991
                },
                {
                    "content": "-",
                    "confidence": 0.413
                },
                {
                    "content": "Jun",
                    "confidence": 0.997
                },
                {
                    "content": "2019",
                    "confidence": 0.989
                },
                {
                    "content": "9",
                    "confidence": 0.049
                },
                {
                    "content": "Taipei,",
                    "confidence": 0.949
                },
                {
                    "content": "Taiwan",
                    "confidence": 0.908
                },
                {
                    "content": "got",
                    "confidence": 0.997
                },
                {
                    "content": "in",
                    "confidence": 0.994
                },
                {
                    "content": "touch",
                    "confidence": 0.995
                },
                {
                    "content": "with",
                    "confidence": 0.987
                },
                {
                    "content": "30-",
                    "confidence": 0.618
                },
                {
                    "content": "startup",
                    "confidence": 0.994
                },
                {
                    "content": "teams,",
                    "confidence": 0.991
                },
                {
                    "content": "and",
                    "confidence": 0.997
                },
                {
                    "content": "performed",
                    "confidence": 0.993
                },
                {
                    "content": "due",
                    "confidence": 0.996
                },
                {
                    "content": "diligence",
                    "confidence": 0.957
                },
                {
                    "content": "investigation",
                    "confidence": 0.991
                },
                {
                    "content": "on",
                    "confidence": 0.998
                },
                {
                    "content": "10",
                    "confidence": 0.997
                },
                {
                    "content": "startups",
                    "confidence": 0.991
                },
                {
                    "content": "organized",
                    "confidence": 0.993
                },
                {
                    "content": "2",
                    "confidence": 0.991
                },
                {
                    "content": "sharing",
                    "confidence": 0.994
                },
                {
                    "content": "&",
                    "confidence": 0.98
                },
                {
                    "content": "matching",
                    "confidence": 0.994
                },
                {
                    "content": "activities",
                    "confidence": 0.983
                },
                {
                    "content": "cooperatively,",
                    "confidence": 0.67
                },
                {
                    "content": "and",
                    "confidence": 0.997
                },
                {
                    "content": "attracted",
                    "confidence": 0.992
                },
                {
                    "content": "50+",
                    "confidence": 0.997
                },
                {
                    "content": "participants",
                    "confidence": 0.991
                },
                {
                    "content": "conducted",
                    "confidence": 0.993
                },
                {
                    "content": "investment",
                    "confidence": 0.968
                },
                {
                    "content": "risk",
                    "confidence": 0.985
                },
                {
                    "content": "assessment",
                    "confidence": 0.991
                },
                {
                    "content": "on",
                    "confidence": 0.998
                },
                {
                    "content": "2",
                    "confidence": 0.994
                },
                {
                    "content": "companies,",
                    "confidence": 0.967
                },
                {
                    "content": "and",
                    "confidence": 0.997
                },
                {
                    "content": "competed",
                    "confidence": 0.994
                },
                {
                    "content": "1",
                    "confidence": 0.994
                },
                {
                    "content": "investment",
                    "confidence": 0.992
                },
                {
                    "content": "Motivation:",
                    "confidence": 0.993
                },
                {
                    "content": "to",
                    "confidence": 0.997
                },
                {
                    "content": "understand",
                    "confidence": 0.993
                },
                {
                    "content": "how",
                    "confidence": 0.997
                },
                {
                    "content": "venture",
                    "confidence": 0.995
                },
                {
                    "content": "capitalists",
                    "confidence": 0.97
                },
                {
                    "content": "analyze",
                    "confidence": 0.965
                },
                {
                    "content": "startups",
                    "confidence": 0.991
                },
                {
                    "content": "while",
                    "confidence": 0.997
                },
                {
                    "content": "making",
                    "confidence": 0.996
                },
                {
                    "content": "investment",
                    "confidence": 0.992
                },
                {
                    "content": "decisions",
                    "confidence": 0.991
                },
                {
                    "content": "R",
                    "confidence": 0.991
                },
                {
                    "content": "ROOICIE",
                    "confidence": 0.664
                },
                {
                    "content": "FUND",
                    "confidence": 0.612
                },
                {
                    "content": "Education",
                    "confidence": 0.993
                },
                {
                    "content": "National",
                    "confidence": 0.991
                },
                {
                    "content": "Tsing",
                    "confidence": 0.995
                },
                {
                    "content": "Hua",
                    "confidence": 0.997
                },
                {
                    "content": "University",
                    "confidence": 0.994
                },
                {
                    "content": ".",
                    "confidence": 0.7
                },
                {
                    "content": "BEc",
                    "confidence": 0.994
                },
                {
                    "content": ".",
                    "confidence": 0.66
                },
                {
                    "content": "2015",
                    "confidence": 0.983
                },
                {
                    "content": "-",
                    "confidence": 0.552
                },
                {
                    "content": "2019",
                    "confidence": 0.987
                },
                {
                    "content": "Major",
                    "confidence": 0.993
                },
                {
                    "content": ":",
                    "confidence": 0.994
                },
                {
                    "content": "Economics",
                    "confidence": 0.939
                },
                {
                    "content": ".",
                    "confidence": 0.785
                },
                {
                    "content": "GPA",
                    "confidence": 0.997
                },
                {
                    "content": ":",
                    "confidence": 0.994
                },
                {
                    "content": "3.92",
                    "confidence": 0.991
                },
                {
                    "content": "/",
                    "confidence": 0.995
                },
                {
                    "content": "4.3",
                    "confidence": 0.963
                },
                {
                    "content": "0",
                    "confidence": 0.011
                },
                {
                    "content": "Hsinchu,",
                    "confidence": 0.949
                },
                {
                    "content": "Taiwan",
                    "confidence": 0.629
                }
            ]
        }
    ]
}